{"list":[{"timeinfo":{"datetime":"2020-08-07 06:00:00","date":"8/7","time":"15"},"temp":35.5,"weather":{"main":"Clouds","icon":"04d","id":"803"}},{"timeinfo":{"datetime":"2020-08-07 09:00:00","date":"8/7","time":"18"},"temp":34.5,"weather":{"main":"Clouds","icon":"04d","id":"804"}},{"timeinfo":{"datetime":"2020-08-07 12:00:00","date":"8/7","time":"21"},"temp":32.0,"weather":{"main":"Clouds","icon":"04n","id":"804"}},{"timeinfo":{"datetime":"2020-08-07 15:00:00","date":"8/8","time":"0"},"temp":30.9,"weather":{"main":"Rain","icon":"10n","id":"500"}},{"timeinfo":{"datetime":"2020-08-07 18:00:00","date":"8/8","time":"3"},"temp":28.8,"weather":{"main":"Rain","icon":"10n","id":"500"}},{"timeinfo":{"datetime":"2020-08-07 21:00:00","date":"8/8","time":"6"},"temp":28.7,"weather":{"main":"Clouds","icon":"04d","id":"804"}},{"timeinfo":{"datetime":"2020-08-08 00:00:00","date":"8/8","time":"9"},"temp":29.6,"weather":{"main":"Clouds","icon":"04d","id":"804"}},{"timeinfo":{"datetime":"2020-08-08 03:00:00","date":"8/8","time":"12"},"temp":32.0,"weather":{"main":"Clouds","icon":"04d","id":"804"}},{"timeinfo":{"datetime":"2020-08-08 06:00:00","date":"8/8","time":"15"},"temp":34.2,"weather":{"main":"Clouds","icon":"04d","id":"804"}},{"timeinfo":{"datetime":"2020-08-08 09:00:00","date":"8/8","time":"18"},"temp":32.5,"weather":{"main":"Clouds","icon":"03d","id":"802"}},{"timeinfo":{"datetime":"2020-08-08 12:00:00","date":"8/8","time":"21"},"temp":30.3,"weather":{"main":"Clouds","icon":"04n","id":"803"}},{"timeinfo":{"datetime":"2020-08-08 15:00:00","date":"8/9","time":"0"},"temp":29.1,"weather":{"main":"Clouds","icon":"04n","id":"803"}},{"timeinfo":{"datetime":"2020-08-08 18:00:00","date":"8/9","time":"3"},"temp":28.2,"weather":{"main":"Clouds","icon":"04n","id":"804"}},{"timeinfo":{"datetime":"2020-08-08 21:00:00","date":"8/9","time":"6"},"temp":28.1,"weather":{"main":"Clouds","icon":"04d","id":"804"}},{"timeinfo":{"datetime":"2020-08-09 00:00:00","date":"8/9","time":"9"},"temp":30.9,"weather":{"main":"Clouds","icon":"04d","id":"804"}},{"timeinfo":{"datetime":"2020-08-09 03:00:00","date":"8/9","time":"12"},"temp":34.5,"weather":{"main":"Clouds","icon":"04d","id":"804"}},{"timeinfo":{"datetime":"2020-08-09 06:00:00","date":"8/9","time":"15"},"temp":35.4,"weather":{"main":"Clouds","icon":"04d","id":"804"}},{"timeinfo":{"datetime":"2020-08-09 09:00:00","date":"8/9","time":"18"},"temp":33.8,"weather":{"main":"Clouds","icon":"04d","id":"804"}},{"timeinfo":{"datetime":"2020-08-09 12:00:00","date":"8/9","time":"21"},"temp":32.4,"weather":{"main":"Clouds","icon":"04n","id":"804"}},{"timeinfo":{"datetime":"2020-08-09 15:00:00","date":"8/10","time":"0"},"temp":31.2,"weather":{"main":"Clouds","icon":"04n","id":"804"}},{"timeinfo":{"datetime":"2020-08-09 18:00:00","date":"8/10","time":"3"},"temp":29.7,"weather":{"main":"Clouds","icon":"04n","id":"804"}},{"timeinfo":{"datetime":"2020-08-09 21:00:00","date":"8/10","time":"6"},"temp":29.4,"weather":{"main":"Clouds","icon":"04d","id":"804"}},{"timeinfo":{"datetime":"2020-08-10 00:00:00","date":"8/10","time":"9"},"temp":32.0,"weather":{"main":"Clouds","icon":"04d","id":"804"}},{"timeinfo":{"datetime":"2020-08-10 03:00:00","date":"8/10","time":"12"},"temp":34.8,"weather":{"main":"Clouds","icon":"04d","id":"804"}},{"timeinfo":{"datetime":"2020-08-10 06:00:00","date":"8/10","time":"15"},"temp":35.2,"weather":{"main":"Clouds","icon":"04d","id":"804"}},{"timeinfo":{"datetime":"2020-08-10 09:00:00","date":"8/10","time":"18"},"temp":34.1,"weather":{"main":"Rain","icon":"10d","id":"500"}},{"timeinfo":{"datetime":"2020-08-10 12:00:00","date":"8/10","time":"21"},"temp":33.0,"weather":{"main":"Clouds","icon":"04n","id":"804"}},{"timeinfo":{"datetime":"2020-08-10 15:00:00","date":"8/11","time":"0"},"temp":32.0,"weather":{"main":"Clouds","icon":"04n","id":"804"}},{"timeinfo":{"datetime":"2020-08-10 18:00:00","date":"8/11","time":"3"},"temp":30.8,"weather":{"main":"Clouds","icon":"04n","id":"803"}},{"timeinfo":{"datetime":"2020-08-10 21:00:00","date":"8/11","time":"6"},"temp":30.3,"weather":{"main":"Clear","icon":"01d","id":"800"}},{"timeinfo":{"datetime":"2020-08-11 00:00:00","date":"8/11","time":"9"},"temp":33.7,"weather":{"main":"Clear","icon":"01d","id":"800"}},{"timeinfo":{"datetime":"2020-08-11 03:00:00","date":"8/11","time":"12"},"temp":37.7,"weather":{"main":"Clear","icon":"01d","id":"800"}},{"timeinfo":{"datetime":"2020-08-11 06:00:00","date":"8/11","time":"15"},"temp":38.9,"weather":{"main":"Clear","icon":"01d","id":"800"}},{"timeinfo":{"datetime":"2020-08-11 09:00:00","date":"8/11","time":"18"},"temp":35.8,"weather":{"main":"Clear","icon":"01d","id":"800"}},{"timeinfo":{"datetime":"2020-08-11 12:00:00","date":"8/11","time":"21"},"temp":33.0,"weather":{"main":"Clear","icon":"01n","id":"800"}},{"timeinfo":{"datetime":"2020-08-11 15:00:00","date":"8/12","time":"0"},"temp":32.4,"weather":{"main":"Clear","icon":"01n","id":"800"}},{"timeinfo":{"datetime":"2020-08-11 18:00:00","date":"8/12","time":"3"},"temp":31.6,"weather":{"main":"Clear","icon":"01n","id":"800"}},{"timeinfo":{"datetime":"2020-08-11 21:00:00","date":"8/12","time":"6"},"temp":31.4,"weather":{"main":"Clear","icon":"01d","id":"800"}},{"timeinfo":{"datetime":"2020-08-12 00:00:00","date":"8/12","time":"9"},"temp":34.1,"weather":{"main":"Clear","icon":"01d","id":"800"}},{"timeinfo":{"datetime":"2020-08-12 03:00:00","date":"8/12","time":"12"},"temp":36.8,"weather":{"main":"Clear","icon":"01d","id":"800"}}]}
